traceai_google_genai/__init__.py
traceai_google_genai/_request_attributes_extractor.py
traceai_google_genai/_response_attributes_extractor.py
traceai_google_genai/_stream.py
traceai_google_genai/_utils.py
traceai_google_genai/_with_span.py
traceai_google_genai/_wrappers.py
traceai_google_genai/package.py
traceai_google_genai/version.py
traceai_google_genai-0.1.1.dist-info/METADATA
traceai_google_genai-0.1.1.dist-info/WHEEL
traceai_google_genai-0.1.1.dist-info/RECORD
